[
    {
        "parent_working_name": "sports",
        "working_name": "baseball",
        "display_name": "Baseball"
    },
    {
        "parent_working_name": "sports",
        "working_name": "basketball",
        "display_name": "Basketball"
    },
    {
        "parent_working_name": "sports",
        "working_name": "cross_country",
        "display_name": "Cross Country"
    },
    {
        "parent_working_name": "sports",
        "working_name": "fencing",
        "display_name": "Fencing"
    },
    {
        "parent_working_name": "sports",
        "working_name": "football",
        "display_name": "Football"
    },
    {
        "parent_working_name": "sports",
        "working_name": "gymnastics",
        "display_name": "Gymnastics"
    },
    {
        "parent_working_name": "sports",
        "working_name": "hockey",
        "display_name": "Hockey"
    },
    {
        "parent_working_name": "sports",
        "working_name": "soccer",
        "display_name": "Soccer"
    },
    {
        "parent_working_name": "sports",
        "working_name": "track_field",
        "display_name": "Track & Field"
    },
    {
        "parent_working_name": "sports",
        "working_name": "volleyball",
        "display_name": "Volleyball"
    },
    {
        "parent_working_name": "sports",
        "working_name": "wrestling",
        "display_name": "Wrestling"
    },
    {
        "parent_working_name": "yearbooks",
        "working_name": "covers",
        "display_name": "Covers"
    },
    {
        "parent_working_name": "yearbooks",
        "working_name": "jh_7071",
        "display_name": "Wayzata Junior High Yearbook 1970-71"
    },
    {
        "parent_working_name": "yearbooks",
        "working_name": "jh_7172",
        "display_name": "Wayzata Junior High Yearbook 1971-72"
    },
    {
        "parent_working_name": "yearbooks",
        "working_name": "jh_7273",
        "display_name": "Wayzata Junior High Yearbook 1972-73"
    },
    {
        "parent_working_name": "2006",
        "working_name": "reunion",
        "display_name": "Reunion"
    },
    {
        "parent_working_name": "2006",
        "working_name": "tourney",
        "display_name": "Tourney for Ted (Schultz) Memorial Golf Tournament"
    },
    {
        "parent_working_name": "2006",
        "working_name": "legion",
        "display_name": "Reunion Eve at the Wayzata Legion"
    },
    {
        "parent_working_name": "2011",
        "working_name": "reunion",
        "display_name": "Reunion"
    },
    {
        "parent_working_name": "2011",
        "working_name": "reunion_committee",
        "display_name": "Reunion Committee"
    },
    {
        "parent_working_name": "2011",
        "working_name": "tourney",
        "display_name": "Tourney for Ted (Schultz) Memorial Golf Tournament"
    },
    {
        "parent_working_name": "2011",
        "working_name": "legion",
        "display_name": "Reunion Eve at the Wayzata Legion"
    },
    {
        "parent_working_name": "2016",
        "working_name": "reunion",
        "display_name": "Reunion"
    },
    {
        "parent_working_name": "2016",
        "working_name": "legion",
        "display_name": "Reunion Eve at the Wayzata Legion"
    }
]